test_project_client/openapi/openapi/__init__.py
test_project_client/openapi/openapi/dome.primitives.json
test_project_client/openapi/openapi/dome.raw.json
test_project_client/openapi/openapi/middesk.primitives.json
test_project_client/openapi/openapi/middesk.raw.json
test_project_client/openapi/openapi/openai.json
test_project_client/openapi/openapi/openai.primitives.json
test_project_client/openapi/openapi/openai.raw.json
test_project_client/openapi/openapi/runpod.primitives.json
test_project_client/openapi/openapi/runpod.raw.json
test_project_client/src/__init__.py
test_project_client/src/api/__init__.py
test_project_client/src/api/dependencies.py
test_project_client/src/api/dome/__init__.py
test_project_client/src/api/dome/routes.py
test_project_client/src/api/middesk/__init__.py
test_project_client/src/api/middesk/routes.py
test_project_client/src/api/openai/__init__.py
test_project_client/src/api/openai/routes.py
test_project_client/src/api/runpod/__init__.py
test_project_client/src/api/runpod/routes.py
test_project_client/src/api/server.py
test_project_client/src/business/__init__.py
test_project_client/src/business/context.py
test_project_client/src/business/dome/__init__.py
test_project_client/src/business/dome/actions/__init__.py
test_project_client/src/business/dome/agent.py
test_project_client/src/business/dome/types.py
test_project_client/src/business/middesk/__init__.py
test_project_client/src/business/middesk/actions/__init__.py
test_project_client/src/business/middesk/agent.py
test_project_client/src/business/middesk/types.py
test_project_client/src/business/openai/__init__.py
test_project_client/src/business/openai/actions/__init__.py
test_project_client/src/business/openai/agent.py
test_project_client/src/business/openai/types.py
test_project_client/src/business/runpod/__init__.py
test_project_client/src/business/runpod/actions/__init__.py
test_project_client/src/business/runpod/agent.py
test_project_client/src/business/runpod/types.py
test_project_client-0.3.11.dist-info/METADATA
test_project_client-0.3.11.dist-info/WHEEL
test_project_client-0.3.11.dist-info/RECORD
